mcp_edge_tts/__init__.py
mcp_edge_tts/__main__.py
mcp_edge_tts/audio.py
mcp_edge_tts/config.py
mcp_edge_tts/server.py
mcp_edge_tts/tts.py
mcp_edge_tts-0.1.1.dist-info/METADATA
mcp_edge_tts-0.1.1.dist-info/WHEEL
mcp_edge_tts-0.1.1.dist-info/entry_points.txt
mcp_edge_tts-0.1.1.dist-info/licenses/LICENSE
mcp_edge_tts-0.1.1.dist-info/RECORD
