Metadata-Version: 2.4
Name: mcp-edge-tts
Version: 0.1.1
Summary: Minimal cross-platform MCP server for text-to-speech using Microsoft Edge TTS
Project-URL: Homepage, https://github.com/s-n-n/edge-tts-mcp
Project-URL: Repository, https://github.com/s-n-n/edge-tts-mcp
Project-URL: Issues, https://github.com/s-n-n/edge-tts-mcp/issues
Author-email: Nikolay <nikolay.savenets@gmail.com>
License-Expression: MIT
License-File: LICENSE
Keywords: ai,anthropic,claude,claude-code,claude-desktop,edge-tts,mcp,speak,speech,text-to-speech,tts,voice
Classifier: Development Status :: 4 - Beta
Classifier: Intended Audience :: Developers
Classifier: License :: OSI Approved :: MIT License
Classifier: Operating System :: OS Independent
Classifier: Programming Language :: Python :: 3
Classifier: Programming Language :: Python :: 3.10
Classifier: Programming Language :: Python :: 3.11
Classifier: Programming Language :: Python :: 3.12
Classifier: Programming Language :: Python :: 3.13
Classifier: Topic :: Multimedia :: Sound/Audio :: Speech
Requires-Python: >=3.10
Requires-Dist: edge-tts>=6.1.0
Requires-Dist: mcp>=1.0.0
Requires-Dist: pydantic-settings>=2.0.0
Provides-Extra: dev
Requires-Dist: mypy>=1.0.0; extra == 'dev'
Requires-Dist: pytest-asyncio>=0.21.0; extra == 'dev'
Requires-Dist: pytest>=7.0.0; extra == 'dev'
Requires-Dist: ruff>=0.1.0; extra == 'dev'
